sanic_sass/__init__.py
sanic_sass-0.1.0.dist-info/LICENSE
sanic_sass-0.1.0.dist-info/METADATA
sanic_sass-0.1.0.dist-info/WHEEL
sanic_sass-0.1.0.dist-info/top_level.txt
sanic_sass-0.1.0.dist-info/RECORD
